jw_pypi_sandbox/__init__.py
jw_pypi_sandbox/main.py
jw_pypi_sandbox-0.1.2.dist-info/LICENSE
jw_pypi_sandbox-0.1.2.dist-info/METADATA
jw_pypi_sandbox-0.1.2.dist-info/WHEEL
jw_pypi_sandbox-0.1.2.dist-info/top_level.txt
jw_pypi_sandbox-0.1.2.dist-info/RECORD
