Metadata-Version: 2.1
Name: jw-pypi-sandbox
Version: 0.1.2
Summary: sb
Author: JW
Author-email: JW@code.com
Classifier: Programming Language :: Python :: 3
Classifier: License :: OSI Approved :: MIT License
Classifier: Operating System :: OS Independent
Requires-Python: >=3.7
License-File: LICENSE
Requires-Dist: requests
